cuda/pathfinder/__init__.py
cuda/pathfinder/_version.py
cuda/pathfinder/_dynamic_libs/find_nvidia_dynamic_lib.py
cuda/pathfinder/_dynamic_libs/load_dl_common.py
cuda/pathfinder/_dynamic_libs/load_dl_linux.py
cuda/pathfinder/_dynamic_libs/load_dl_windows.py
cuda/pathfinder/_dynamic_libs/load_nvidia_dynamic_lib.py
cuda/pathfinder/_dynamic_libs/supported_nvidia_libs.py
cuda/pathfinder/_headers/find_nvidia_headers.py
cuda/pathfinder/_headers/supported_nvidia_headers.py
cuda/pathfinder/_utils/env_vars.py
cuda/pathfinder/_utils/find_site_packages_dll.py
cuda/pathfinder/_utils/find_site_packages_so.py
cuda/pathfinder/_utils/find_sub_dirs.py
cuda/pathfinder/_utils/platform_aware.py
cuda_pathfinder-1.3.1.dist-info/licenses/LICENSE
cuda_pathfinder-1.3.1.dist-info/METADATA
cuda_pathfinder-1.3.1.dist-info/WHEEL
cuda_pathfinder-1.3.1.dist-info/top_level.txt
cuda_pathfinder-1.3.1.dist-info/RECORD
