Metadata-Version: 2.4
Name: cuda-pathfinder
Version: 1.3.1
Summary: Pathfinder for CUDA components
Author-email: NVIDIA Corporation <cuda-python-conduct@nvidia.com>
License-Expression: Apache-2.0
Project-URL: Repository, https://github.com/NVIDIA/cuda-python
Project-URL: Documentation, https://nvidia.github.io/cuda-python/
Requires-Python: >=3.9
License-File: LICENSE
Dynamic: license-file
